{"extracted_information": "以下是Flutter项目的pubspec.yaml文件的完整内容：\n\nname: novelforge_client\ndescription: NovelForge Sentinel Pro - AI小说创作桌面软件\npublish_to: 'none'\nversion: 1.0.0+1\nenvironment:\n  sdk: '>=3.1.0 <4.0.0'\ndependencies:\n  flutter:\n    sdk: flutter\n  # UI框架和主题\n  cupertino_icons: ^1.0.2\n  material_color_utilities: ^0.5.0\n  # Supabase集成\n  supabase_flutter: ^1.10.25\n  # 本地存储和安全\n  flutter_secure_storage: ^9.0.0\n  shared_preferences: ^2.2.2\n  path_provider: ^2.1.1\n  # 网络请求\n  dio: ^5.3.2\n  http: ^1.1.0\n  # 状态管理\n  provider: ^6.0.5\n  riverpod: ^2.4.5\n  flutter_riverpod: ^2.4.5\n  # 加密和安全\n  crypto: ^3.0.3\n  encrypt: ^5.0.1\n  device_info_plus: ^9.1.0\n  # 文件操作\n  file_picker: ^5.5.0\n  permission_handler: ^11.0.1\n  # UI增强\n  animated_text_kit: ^4.2.2\n  lottie: ^2.7.0\n  flutter_animate: ^4.2.0+1\n  # 桌面特定\n  window_manager: ^0.3.7\n  desktop_lifecycle: ^0.1.0\n  # 工具类\n  uuid: ^4.1.0\n  intl: ^0.18.1\n  logger: ^2.0.2+1\ndev_dependencies:\n  flutter_test:\n    sdk: flutter\n  flutter_lints: ^2.0.0\n  build_runner: ^2.4.7\nflutter:\n  uses-material-design: true\n  assets:\n    - assets/images/\n    - assets/fonts/\n    - assets/icons/\n    - assets/animations/\n  fonts:\n    - family: Orbitron\n      fonts:\n        - asset: assets/fonts/Orbitron-Regular.ttf\n        - asset: assets/fonts/Orbitron-Bold.ttf\n          weight: 700\n    - family: RobotoMono\n      fonts:\n        - asset: assets/fonts/RobotoMono-Regular.ttf\n        - asset: assets/fonts/RobotoMono-Bold.ttf\n          weight: 700", "specifications": {"name": "novelforge_client", "description": "NovelForge Sentinel Pro - AI小说创作桌面软件", "publish_to": "none", "version": "1.0.0+1", "environment": {"sdk": "'>=3.1.0 <4.0.0'"}}, "pricing": {}, "features": [], "statistics": {}, "temporal_info": {}, "geographical_data": {}, "references": []}